{
  "data": {
    "Популярные услуги": {
      "Регулировка фурнитуры": "1300₽",
      "Смазка фурнитуры": "400₽",
      "Установка пылевой заглушки": "от 500₽ м/п",
      "Замена ручки": "от 1500₽",
      "Пропенка отлива, козырька, швов": "850₽ м/п",
      "Отделка наружних швов (стиз-А)": "950₽ м/п",
      "Замена уплотнителя": "от 600₽ м/п"
    },
    "Замена стеклопакета и фурнитуры": {
      "Замена стеклопакетов однокамерный": "8000₽",
      "Замена стеклопакетов двухкамерный": "10000₽",
      "Замена ф-ры на окно": "9500₽",
      "Замена ф-ры на балконную дверь": "1100₽",
      "Замена ф-ры штульпового окна": "15000₽",
      "Частичная замена ф-ры": "от 4200₽",
      "Замена стекла деревянных стеклопакетов": "от 12000₽"
    },
    "Всё для москитных сеток": {
      "Замер, установка м/с": "от 3000₽",
      "Перетяжка м/с": "1300₽",
      "Замена уголков, ручек, крепежей, на м/с": "250₽/шт"
    },
    "Откосы, отливы, подоконники и доп.услуги": {
      "Двухстворчатое окно": "8000₽",
      "Установка подоконников": "3750₽ м/п",
      "Установка отливов": "3750₽ м/п",
      "Набор по уходу за окнами": "2200₽",
      "Установка ручки с замком с ключом (защита от детей)": "3000₽",
      "Установка защёлки с ручкой на балконную дверь": "1750₽",
      "Заглушка на подоконник, отлив, петли": "от 350₽шт",
      "Выезд мастера": "500₽",
      "Установка регулятора проветривания окна": "от 1500₽",
      "Установка двойной ручки на балконную дверь": "4000₽",
      "Сервисное обслуживание на 3 года": "20000₽"
    }
  },
  "remark": {
    "Сервисное обслуживание": "чистка, смазка фурнитуры, смазка уплотнителя, проф осмотр, регулировка, два раза в год",
    "Замер, установка м/с": "антикошка, м/с на балконную дверь, м/с на петлях с магнитами, ролетная м/с, и т.д, цена оговаривается с мастером",
    "Установка подоконников": "ламинированные, каменные, глянцевые, подоконники из столешницы, цена оговаривается  с мастером"
  }
}